myMain.py
wzxc1/__init__.py
wzxc1/myMain.py
wzxcjx/__init__.py
wzxcjx/myMain.py
wzxc-0.1.4.dist-info/LICENSE.txt
wzxc-0.1.4.dist-info/METADATA
wzxc-0.1.4.dist-info/WHEEL
wzxc-0.1.4.dist-info/top_level.txt
wzxc-0.1.4.dist-info/RECORD
