Metadata-Version: 2.1
Name: wzxc
Version: 0.1.4
Summary: 怎么说呢
Home-page: https://github.com/linlenan/wzxc.git
Author: Linln
Author-email: 454128458@qq.com
License: MIT
Platform: UNKNOWN
Classifier: License :: OSI Approved :: MIT License
Classifier: Programming Language :: Python
Classifier: Programming Language :: Python :: 3
Classifier: Programming Language :: Python :: 3.6
Classifier: Programming Language :: Python :: Implementation :: CPython
Classifier: Programming Language :: Python :: Implementation :: PyPy
Requires-Python: >=3.6.0
